webwatch/__init__.py
webwatch/cli.py
webwatch/notifications.py
webwatch/watcher.py
webwatch/watcher_test.py
webwatch-0.1.0.dist-info/WHEEL
webwatch-0.1.0.dist-info/entry_points.txt
webwatch-0.1.0.dist-info/METADATA
webwatch-0.1.0.dist-info/RECORD
