Metadata-Version: 2.3
Name: webwatch
Version: 0.1.0
Summary: A simple CLI tool to watch a web page for changes.
Author: Vincent Pfister
Author-email: Vincent Pfister <vincent.pfister@raisepartner.com>
License: MIT License
Classifier: Programming Language :: Python :: 3
Classifier: License :: OSI Approved :: MIT License
Classifier: Operating System :: OS Independent
Requires-Dist: click>=8.0
Requires-Dist: cssselect>=1.3.0
Requires-Dist: httpx>=0.25
Requires-Dist: loguru>=0.7
Requires-Dist: lxml>=4.9
Requires-Python: >=3.10
